simple_geo/__init__.py
simple_geo/admin.py
simple_geo/models.py
simple_geo/settings.py
simple_geo/utils.py
django_simple_geo-0.4.4.dist-info/AUTHORS
django_simple_geo-0.4.4.dist-info/LICENSE
django_simple_geo-0.4.4.dist-info/METADATA
django_simple_geo-0.4.4.dist-info/WHEEL
django_simple_geo-0.4.4.dist-info/top_level.txt
django_simple_geo-0.4.4.dist-info/RECORD
