Metadata-Version: 2.1
Name: django-simple-geo
Version: 0.4.4
Summary: Simple Django city, state, country geo-spatially aware model and utilities.
Home-page: http://github.com/jaddison/django-simple-geo
Author: James Addison
Author-email: addi00+github.com@gmail.com
License: BSD
Keywords: django,geo,gis,geodjango,geocoding,longitude,latitude,geospatial,cities,coordinates
Classifier: Development Status :: 4 - Beta
Classifier: License :: OSI Approved :: BSD License
Classifier: Intended Audience :: Developers
Classifier: Environment :: Web Environment
Classifier: Programming Language :: Python
Classifier: Framework :: Django
Classifier: Topic :: Internet :: WWW/HTTP :: WSGI
License-File: LICENSE
License-File: AUTHORS
